README.md
setup.py
Development_tools_alex2.egg-info/PKG-INFO
Development_tools_alex2.egg-info/SOURCES.txt
Development_tools_alex2.egg-info/dependency_links.txt
Development_tools_alex2.egg-info/entry_points.txt
Development_tools_alex2.egg-info/namespace_packages.txt
Development_tools_alex2.egg-info/requires.txt
Development_tools_alex2.egg-info/top_level.txt
orangecontrib/__init__.py
orangecontrib/development_tools/__init__.py
orangecontrib/development_tools/widgets/__init__.py
orangecontrib/development_tools/widgets/icons/Chatbot.svg
orangecontrib/development_tools/widgets/icons/DocumentEater.svg
orangecontrib/development_tools/widgets/icons/Embeddings.svg
orangecontrib/development_tools/widgets/icons/LanguageModel.svg
orangecontrib/development_tools/widgets/icons/Logo_HKH.svg
orangecontrib/development_tools/widgets/icons/TextPreprocessing.svg
orangecontrib/development_tools/widgets/icons/file-transfer.png
orangecontrib/development_tools/widgets/icons/goto.png
orangecontrib/development_tools/widgets/icons/input.png
orangecontrib/development_tools/widgets/icons/jcm_open_file_resize_alpha_channel.png
orangecontrib/development_tools/widgets/icons/output.png
orangecontrib/development_tools/widgets/icons/subworkflow_output.png
orangecontrib/development_tools/widgets/icons/tool.png
orangecontrib/development_tools/widgets/widget_designer/goto.ui
orangecontrib/development_tools/widgets/widget_designer/load_tab.ui
orangecontrib/development_tools/widgets/widget_designer/orange_sub_workflow.ui
orangecontrib/development_tools/widgets/widget_designer/subworkflow_input_ui.ui
orangecontrib/development_tools/widgets/widget_designer/subworkflow_output_ui.ui