Metadata-Version: 1.0
Name: Development-tools-alex2
Version: 0.0.1
Summary: A package to built-in widgets (Input data, output data, subworkflow widgets). Also goto widget and others
Home-page: UNKNOWN
Author: HKH
Author-email: UNKNOWN
License: UNKNOWN
Keywords: orange3 add-on
Platform: UNKNOWN
